README.txt
setup.py
TOPSIS_SUKRITI_401803026/__init__.py
TOPSIS_SUKRITI_401803026.egg-info/PKG-INFO
TOPSIS_SUKRITI_401803026.egg-info/SOURCES.txt
TOPSIS_SUKRITI_401803026.egg-info/dependency_links.txt
TOPSIS_SUKRITI_401803026.egg-info/requires.txt
TOPSIS_SUKRITI_401803026.egg-info/top_level.txt