Metadata-Version: 2.1
Name: TOPSIS-SUKRITI-401803026
Version: 0.0.4
Summary: TOPSIS evaluator for given data. Enter all arguments as strings
Home-page: https://pypi.org/project/TOPSIS-SUKRITI-401803026/0.0.1/
Author: Sukriti Sharma
Author-email: ssharma_bemba18@thapar.edu
License: MIT
Keywords: calculator
Platform: UNKNOWN
Classifier: Development Status :: 5 - Production/Stable
Classifier: Intended Audience :: Education
Classifier: Operating System :: Microsoft :: Windows :: Windows 10
Classifier: License :: OSI Approved :: MIT License
Classifier: Programming Language :: Python :: 3
